Metadata-Version: 2.1
Name: nsgpytorch
Version: 0.1.0
Summary: A collection of Non-stationary GP models
Home-page: https://github.com/patel-zeel/nsgpytorch
Author: Zeel B Patel
Author-email: patel_zeel@iitgn.ac.in
License: MIT
Platform: UNKNOWN
Requires-Python: >=3.6
License-File: LICENSE
